customs_inspector/__init__.py
customs_inspector/audit.py
customs_inspector/plugin.py
customs_inspector/server.py
customs_inspector/static/diff.html
customs_inspector/static/editor.main.css
customs_inspector/static/editor.main.js
customs_inspector/static/editor.main.nls.js
customs_inspector/static/footer.template
customs_inspector/static/header.template
customs_inspector/static/loader.js
customs_inspector/static/stop.template
customs_inspector/static/vs/base/browser/ui/codicons/codicon/codicon.ttf
customs_inspector/static/vs/base/common/worker/simpleWorker.nls.de.js
customs_inspector/static/vs/base/common/worker/simpleWorker.nls.es.js
customs_inspector/static/vs/base/common/worker/simpleWorker.nls.fr.js
customs_inspector/static/vs/base/common/worker/simpleWorker.nls.it.js
customs_inspector/static/vs/base/common/worker/simpleWorker.nls.ja.js
customs_inspector/static/vs/base/common/worker/simpleWorker.nls.js
customs_inspector/static/vs/base/common/worker/simpleWorker.nls.ko.js
customs_inspector/static/vs/base/common/worker/simpleWorker.nls.ru.js
customs_inspector/static/vs/base/common/worker/simpleWorker.nls.zh-cn.js
customs_inspector/static/vs/base/common/worker/simpleWorker.nls.zh-tw.js
customs_inspector/static/vs/base/worker/workerMain.js
customs_inspector/static/vs/basic-languages/python/python.js
customs_inspector/static/vs/editor/editor.main.css
customs_inspector/static/vs/editor/editor.main.js
customs_inspector/static/vs/editor/editor.main.nls.de.js
customs_inspector/static/vs/editor/editor.main.nls.es.js
customs_inspector/static/vs/editor/editor.main.nls.fr.js
customs_inspector/static/vs/editor/editor.main.nls.it.js
customs_inspector/static/vs/editor/editor.main.nls.ja.js
customs_inspector/static/vs/editor/editor.main.nls.js
customs_inspector/static/vs/editor/editor.main.nls.ko.js
customs_inspector/static/vs/editor/editor.main.nls.ru.js
customs_inspector/static/vs/editor/editor.main.nls.zh-cn.js
customs_inspector/static/vs/editor/editor.main.nls.zh-tw.js
customs_inspector-0.2.2.dist-info/LICENSE
customs_inspector-0.2.2.dist-info/METADATA
customs_inspector-0.2.2.dist-info/WHEEL
customs_inspector-0.2.2.dist-info/entry_points.txt
customs_inspector-0.2.2.dist-info/RECORD
