Metadata-Version: 2.1
Name: customs-inspector
Version: 0.2.2
Summary: Override Poetry's update command to audit packages before they are updated
License: GPL-3.0
Author: aarnav
Author-email: aarnavbos@gmail.com
Requires-Python: >=3.7,<4.0
Classifier: License :: OSI Approved :: GNU General Public License v3 (GPLv3)
Classifier: Programming Language :: Python :: 3
Classifier: Programming Language :: Python :: 3.7
Classifier: Programming Language :: Python :: 3.8
Classifier: Programming Language :: Python :: 3.9
Classifier: Programming Language :: Python :: 3.10
Classifier: Programming Language :: Python :: 3.11
Requires-Dist: bottle (>=0.12.25,<0.13.0)
Requires-Dist: poetry (>=1.4.0,<2.0.0)
